LeetcodeTijieItcharge/README.md
LeetcodeTijieItcharge/__init__.py
LeetcodeTijieItcharge/__main__.py
LeetcodeTijieItcharge/file.epub
LeetcodeTijieItcharge/index.html
LeetcodeTijieItcharge/css/__init__.py
LeetcodeTijieItcharge/css/annotations.css
LeetcodeTijieItcharge/css/main.css
LeetcodeTijieItcharge/css/normalize.css
LeetcodeTijieItcharge/css/popup.css
LeetcodeTijieItcharge/font/__init__.py
LeetcodeTijieItcharge/font/fontello.eot
LeetcodeTijieItcharge/font/fontello.svg
LeetcodeTijieItcharge/font/fontello.ttf
LeetcodeTijieItcharge/font/fontello.woff
LeetcodeTijieItcharge/img/__init__.py
LeetcodeTijieItcharge/img/annotator-glyph-sprite.png
LeetcodeTijieItcharge/img/annotator-icon-sprite.png
LeetcodeTijieItcharge/img/apple-touch-icon.png
LeetcodeTijieItcharge/img/cancelfullscreen.png
LeetcodeTijieItcharge/img/close.png
LeetcodeTijieItcharge/img/fullscreen.png
LeetcodeTijieItcharge/img/loader.gif
LeetcodeTijieItcharge/img/menu-icon.png
LeetcodeTijieItcharge/img/save.png
LeetcodeTijieItcharge/img/saved.png
LeetcodeTijieItcharge/img/settings-s.png
LeetcodeTijieItcharge/img/settings.png
LeetcodeTijieItcharge/img/star.png
LeetcodeTijieItcharge/js/__init__.py
LeetcodeTijieItcharge/js/epub.js
LeetcodeTijieItcharge/js/epub.min.js
LeetcodeTijieItcharge/js/epub.min.map
LeetcodeTijieItcharge/js/hooks.min.js
LeetcodeTijieItcharge/js/hooks.min.map
LeetcodeTijieItcharge/js/reader.js
LeetcodeTijieItcharge/js/reader.js.map
LeetcodeTijieItcharge/js/reader.min.js
LeetcodeTijieItcharge/js/reader.min.map
LeetcodeTijieItcharge/js/hooks/__init__.py
LeetcodeTijieItcharge/js/hooks/extensions/__init__.py
LeetcodeTijieItcharge/js/hooks/extensions/highlight.js
LeetcodeTijieItcharge/js/libs/__init__.py
LeetcodeTijieItcharge/js/libs/jquery.min.js
LeetcodeTijieItcharge/js/libs/localforage.min.js
LeetcodeTijieItcharge/js/libs/screenfull.js
LeetcodeTijieItcharge/js/libs/screenfull.min.js
LeetcodeTijieItcharge/js/libs/zip.min.js
LeetcodeTijieItcharge/js/plugins/__init__.py
leetcode_tijie_itcharge-2024.3.6.0.dist-info/METADATA
leetcode_tijie_itcharge-2024.3.6.0.dist-info/WHEEL
leetcode_tijie_itcharge-2024.3.6.0.dist-info/entry_points.txt
leetcode_tijie_itcharge-2024.3.6.0.dist-info/top_level.txt
leetcode_tijie_itcharge-2024.3.6.0.dist-info/RECORD
